{
  "template_version": "single-file-legacy-v1",
  "source_file": "示例投标文件.pdf",
  "overview": [
    {
      "项目": "总体结论",
      "内容": "当前材料仅支持文件内一致性核验，外部合规事项需补充材料。",
      "标注状态": "需人工复核",
      "备注": "不作法律定性"
    }
  ],
  "facts": [
    {
      "问题编号": "问题1",
      "问题分类": "招标流程与保证金",
      "提取项": "投标报价",
      "提取结果": "0.64",
      "是否提取成功": "是",
      "信息归属判断": "当前投标文件内容",
      "文件名": "示例投标文件.pdf",
      "PDF实际页码": "4",
      "文件内印刷页码": "3",
      "自动行号/页面区域": "第4页第8行",
      "原文摘录": "投标报价为0.64",
      "置信度": "高",
      "分析/备注": "示例数据"
    }
  ],
  "unavailable": [],
  "findings": [],
  "personnel": [],
  "bases": [],
  "required_materials": []
}

